LuenFuwenZhanbuZixueShouce/README.md
LuenFuwenZhanbuZixueShouce/__init__.py
LuenFuwenZhanbuZixueShouce/__main__.py
LuenFuwenZhanbuZixueShouce/file.epub
LuenFuwenZhanbuZixueShouce/index.html
LuenFuwenZhanbuZixueShouce/css/__init__.py
LuenFuwenZhanbuZixueShouce/css/annotations.css
LuenFuwenZhanbuZixueShouce/css/main.css
LuenFuwenZhanbuZixueShouce/css/normalize.css
LuenFuwenZhanbuZixueShouce/css/popup.css
LuenFuwenZhanbuZixueShouce/font/__init__.py
LuenFuwenZhanbuZixueShouce/font/fontello.eot
LuenFuwenZhanbuZixueShouce/font/fontello.svg
LuenFuwenZhanbuZixueShouce/font/fontello.ttf
LuenFuwenZhanbuZixueShouce/font/fontello.woff
LuenFuwenZhanbuZixueShouce/img/__init__.py
LuenFuwenZhanbuZixueShouce/img/annotator-glyph-sprite.png
LuenFuwenZhanbuZixueShouce/img/annotator-icon-sprite.png
LuenFuwenZhanbuZixueShouce/img/apple-touch-icon.png
LuenFuwenZhanbuZixueShouce/img/cancelfullscreen.png
LuenFuwenZhanbuZixueShouce/img/close.png
LuenFuwenZhanbuZixueShouce/img/fullscreen.png
LuenFuwenZhanbuZixueShouce/img/loader.gif
LuenFuwenZhanbuZixueShouce/img/menu-icon.png
LuenFuwenZhanbuZixueShouce/img/save.png
LuenFuwenZhanbuZixueShouce/img/saved.png
LuenFuwenZhanbuZixueShouce/img/settings-s.png
LuenFuwenZhanbuZixueShouce/img/settings.png
LuenFuwenZhanbuZixueShouce/img/star.png
LuenFuwenZhanbuZixueShouce/js/__init__.py
LuenFuwenZhanbuZixueShouce/js/epub.js
LuenFuwenZhanbuZixueShouce/js/epub.min.js
LuenFuwenZhanbuZixueShouce/js/epub.min.map
LuenFuwenZhanbuZixueShouce/js/hooks.min.js
LuenFuwenZhanbuZixueShouce/js/hooks.min.map
LuenFuwenZhanbuZixueShouce/js/reader.js
LuenFuwenZhanbuZixueShouce/js/reader.js.map
LuenFuwenZhanbuZixueShouce/js/reader.min.js
LuenFuwenZhanbuZixueShouce/js/reader.min.map
LuenFuwenZhanbuZixueShouce/js/hooks/__init__.py
LuenFuwenZhanbuZixueShouce/js/hooks/extensions/__init__.py
LuenFuwenZhanbuZixueShouce/js/hooks/extensions/highlight.js
LuenFuwenZhanbuZixueShouce/js/libs/__init__.py
LuenFuwenZhanbuZixueShouce/js/libs/jquery.min.js
luen_fuwen_zhanbu_zixue_shouce-2022.10.17.0.dist-info/METADATA
luen_fuwen_zhanbu_zixue_shouce-2022.10.17.0.dist-info/WHEEL
luen_fuwen_zhanbu_zixue_shouce-2022.10.17.0.dist-info/entry_points.txt
luen_fuwen_zhanbu_zixue_shouce-2022.10.17.0.dist-info/top_level.txt
luen_fuwen_zhanbu_zixue_shouce-2022.10.17.0.dist-info/RECORD
